bocr/__init__.py
bocr/cli.py
bocr/config.py
bocr/ocr.py
bocr/backbones/__init__.py
bocr/backbones/backbone.py
bocr/backbones/llama.py
bocr/backbones/mapping.yaml
bocr/backbones/ollamas.py
bocr/backbones/phi.py
bocr/backbones/qwen.py
bocr/postprocessing/__init__.py
bocr/postprocessing/md.py
bocr/postprocessing/postprocess.py
bocr/preprocessing/__init__.py
bocr/preprocessing/preprocess.py
bocr/utils/__init__.py
bocr/utils/logger.py
bocr-0.2.0.dist-info/LICENSE
bocr-0.2.0.dist-info/METADATA
bocr-0.2.0.dist-info/WHEEL
bocr-0.2.0.dist-info/entry_points.txt
bocr-0.2.0.dist-info/top_level.txt
bocr-0.2.0.dist-info/RECORD
