Metadata-Version: 2.2
Name: bocr
Version: 0.2.0
Summary: A Python package for OCR using Vision LLMs
Author-email: Adrian Phoulady <adrian.phoulady@gmail.com>
License: MIT
Project-URL: Repository, https://github.com/adrianphoulady/bocr
Keywords: ocr,vision,llm,vllm,bocr,text extraction,qwen-vl,llama-vision,phi-vision,ollama
Classifier: Development Status :: 4 - Beta
Classifier: License :: OSI Approved :: MIT License
Classifier: Operating System :: OS Independent
Classifier: Programming Language :: Python :: 3
Classifier: Programming Language :: Python :: 3.8
Classifier: Programming Language :: Python :: 3.9
Classifier: Programming Language :: Python :: 3.10
Classifier: Programming Language :: Python :: 3.11
Classifier: Programming Language :: Python :: 3.12
Classifier: Programming Language :: Python :: 3.13
Classifier: Intended Audience :: Developers
Classifier: Intended Audience :: Science/Research
Classifier: Topic :: Scientific/Engineering :: Artificial Intelligence
Classifier: Topic :: Software Development :: Libraries :: Python Modules
Requires-Python: >=3.8
License-File: LICENSE
Requires-Dist: accelerate>=0.34.0
Requires-Dist: torch<2.6.0,>=2.4.0
Requires-Dist: torchvision<0.21.0,>=0.19.0
Requires-Dist: transformers>=4.49
Requires-Dist: qwen_vl_utils>=0.0.10
Requires-Dist: ollama>=0.1
Requires-Dist: opencv-python-headless>=4.10.0.84
Requires-Dist: pdf2image>=1.16.0
Requires-Dist: pillow>=10.0.0
Requires-Dist: markdown>=3.4.0
Requires-Dist: pypandoc>=1.11
